{"evols":[],"moves":[{"lvl":"1","name":"Disable","type":"normal","cat":"status","power":0,"acc":100},{"lvl":"1","name":"Ominous Wind","type":"ghost","cat":"special","power":60,"acc":100},{"lvl":"11","name":"Quick Attack","type":"normal","cat":"physical","power":40,"acc":100},{"lvl":"20","name":"Hypnosis","type":"psychic","cat":"status","power":0,"acc":60},{"lvl":"29","name":"Feint Attack","type":"dark","cat":"physical","power":60,"acc":0},{"lvl":"38","name":"Nightmare","type":"ghost","cat":"status","power":0,"acc":100},{"lvl":"47","name":"Double Team","type":"normal","cat":"status","power":0,"acc":0},{"lvl":"57","name":"Haze","type":"ice","cat":"status","power":0,"acc":0},{"lvl":"66","name":"Dark Void","type":"dark","cat":"status","power":0,"acc":50},{"lvl":"75","name":"Nasty Plot","type":"dark","cat":"status","power":0,"acc":0},{"lvl":"84","name":"Dream Eater","type":"psychic","cat":"special","power":100,"acc":100},{"lvl":"93","name":"Dark Pulse","type":"dark","cat":"special","power":80,"acc":100}],"pokemons":[{"img":"https:\/\/img.pokemondb.net\/artwork\/darkrai.jpg","name":"Darkrai","stats":{"pokedex":{"num":"491","type":["dark"],"species":"Pitch-Black Pok\u00e9mon","height":"4\u203211\u2033 (1.50m)","weight":"111.3 lbs (50.5 kg)","abilities":["Bad Dreams"]},"training":["2 Special Attack, 1 Speed","3 (0.4% with Pok\u00e9Ball, full HP)","0 (lower than normal)","210","Slow"],"breeding":{"egg-groups":["undiscovered"],"egg-cycles":"120 (base 30,720 steps)\n"},"base-stats":{"hp":{"idk":"70","min":"250","max":"344"},"attack":{"idk":"90","min":"166","max":"306"},"defense":{"idk":"90","min":"166","max":"306"},"sp-atk":{"idk":"135","min":"247","max":"405"},"sp-def":{"idk":"90","min":"166","max":"306"},"speed":{"idk":"125","min":"229","max":"383"}},"type-defenses":{"nor":"","fir":"","wat":"","ele":"","gra":"","ice":"","fig":"2","poi":"","gro":"","fly":"","psy":"0","bug":"2","roc":"","gho":"\u00bd","dra":"","dar":"\u00bd","ste":"","fai":"2"}}}]}