{"evols":[],"moves":[{"lvl":"1","name":"Present","type":"normal","cat":"physical","power":0,"acc":90},{"lvl":"25","name":"Drill Peck","type":"flying","cat":"physical","power":80,"acc":100}],"pokemons":[{"img":"https:\/\/img.pokemondb.net\/artwork\/delibird.jpg","name":"Delibird","stats":{"pokedex":{"num":"225","type":["ice","flying"],"species":"Delivery Pok\u00e9mon","height":"2\u203211\u2033 (0.89m)","weight":"35.3 lbs (16.0 kg)","abilities":["Hustle","Vital Spirit","Insomnia (hidden ability)"]},"training":["1 Speed","45 (5.9% with Pok\u00e9Ball, full HP)","70 (normal)","183","Fast"],"breeding":{"egg-groups":["field","water 1"],"gender":{"male":50,"female":50},"egg-cycles":"20 (base 5,120 steps)\n"},"base-stats":{"hp":{"idk":"45","min":"200","max":"294"},"attack":{"idk":"55","min":"103","max":"229"},"defense":{"idk":"45","min":"85","max":"207"},"sp-atk":{"idk":"65","min":"121","max":"251"},"sp-def":{"idk":"45","min":"85","max":"207"},"speed":{"idk":"75","min":"139","max":"273"}},"type-defenses":{"nor":"","fir":"2","wat":"","ele":"2","gra":"\u00bd","ice":"","fig":"","poi":"","gro":"0","fly":"","psy":"","bug":"\u00bd","roc":"4","gho":"","dra":"","dar":"","ste":"2","fai":""}}}]}