{"evols":[],"moves":[{"lvl":"1","name":"Twister","type":"dragon","cat":"special","power":40,"acc":100},{"lvl":"5","name":"Scary Face","type":"normal","cat":"status","power":0,"acc":100},{"lvl":"15","name":"Ancient Power","type":"rock","cat":"special","power":60,"acc":100},{"lvl":"20","name":"Crunch","type":"dark","cat":"physical","power":80,"acc":100},{"lvl":"30","name":"Air Slash","type":"flying","cat":"special","power":75,"acc":95},{"lvl":"35","name":"Rest","type":"psychic","cat":"status","power":0,"acc":0},{"lvl":"45","name":"Extreme Speed","type":"normal","cat":"physical","power":80,"acc":100},{"lvl":"50","name":"Dragon Pulse","type":"dragon","cat":"special","power":85,"acc":100},{"lvl":"60","name":"Dragon Dance","type":"dragon","cat":"status","power":0,"acc":0},{"lvl":"65","name":"Fly","type":"flying","cat":"physical","power":90,"acc":95},{"lvl":"75","name":"Hyper Voice","type":"normal","cat":"special","power":90,"acc":100},{"lvl":"80","name":"Outrage","type":"dragon","cat":"physical","power":120,"acc":100},{"lvl":"90","name":"Hyper Beam","type":"normal","cat":"special","power":150,"acc":90}],"pokemons":[{"img":"https:\/\/img.pokemondb.net\/artwork\/rayquaza.jpg","name":"Rayquaza","stats":{"pokedex":{"num":"384","type":["dragon","flying"],"species":"Sky High Pok\u00e9mon","height":"23\u20320\u2033 (7.01m)","weight":"455.3 lbs (206.5 kg)","abilities":["Air Lock"]},"training":["2 Attack, 1 Special Attack","3 (0.4% with Pok\u00e9Ball, full HP)","0 (lower than normal)","220","Slow"],"breeding":{"egg-groups":["undiscovered"],"egg-cycles":"120 (base 30,720 steps)\n"},"base-stats":{"hp":{"idk":"105","min":"320","max":"414"},"attack":{"idk":"150","min":"274","max":"438"},"defense":{"idk":"90","min":"166","max":"306"},"sp-atk":{"idk":"150","min":"274","max":"438"},"sp-def":{"idk":"90","min":"166","max":"306"},"speed":{"idk":"95","min":"175","max":"317"}},"type-defenses":{"nor":"","fir":"\u00bd","wat":"\u00bd","ele":"","gra":"\u00bc","ice":"4","fig":"\u00bd","poi":"","gro":"0","fly":"","psy":"","bug":"\u00bd","roc":"2","gho":"","dra":"2","dar":"","ste":"","fai":"2"}}},{"img":"https:\/\/img.pokemondb.net\/artwork\/rayquaza-mega.jpg","name":"Rayquaza Mega","stats":{"pokedex":{"num":"384","type":["dragon","flying"],"species":"Sky High Pok\u00e9mon","height":"35\u20325\u2033 (10.79m)","weight":"864.2 lbs (392.0 kg)","abilities":["Delta Stream"]},"training":["\u2014","\u2014","\u2014","\u2014","\u2014"],"breeding":{"egg-groups":[],"egg-cycles":"\u00e2\u0080\u0094"},"base-stats":{"hp":{"idk":"105","min":"320","max":"414"},"attack":{"idk":"180","min":"328","max":"504"},"defense":{"idk":"100","min":"184","max":"328"},"sp-atk":{"idk":"180","min":"328","max":"504"},"sp-def":{"idk":"100","min":"184","max":"328"},"speed":{"idk":"115","min":"211","max":"361"}},"type-defenses":{"nor":"","fir":"\u00bd","wat":"\u00bd","ele":"","gra":"\u00bc","ice":"4","fig":"\u00bd","poi":"","gro":"0","fly":"","psy":"","bug":"\u00bd","roc":"2","gho":"","dra":"2","dar":"","ste":"","fai":"2"}}}]}